investormate/__init__.py
investormate/version.py
investormate/ai/__init__.py
investormate/ai/anthropic_provider.py
investormate/ai/base_provider.py
investormate/ai/gemini_provider.py
investormate/ai/openai_provider.py
investormate/ai/prompts.py
investormate/ai/response_parser.py
investormate/analysis/__init__.py
investormate/analysis/correlation.py
investormate/analysis/indicators.py
investormate/analysis/ratios.py
investormate/analysis/scores.py
investormate/analysis/sentiment.py
investormate/core/__init__.py
investormate/core/custom_strategy.py
investormate/core/investor.py
investormate/core/market.py
investormate/core/portfolio.py
investormate/core/screener.py
investormate/core/stock.py
investormate/data/__init__.py
investormate/data/constants.py
investormate/data/earnings_transcripts.py
investormate/data/fetchers.py
investormate/data/parsers.py
investormate/documents/__init__.py
investormate/documents/extractors.py
investormate/documents/processors.py
investormate/utils/__init__.py
investormate/utils/exceptions.py
investormate/utils/formatters.py
investormate/utils/helpers.py
investormate/utils/validators.py
investormate-0.2.0.dist-info/licenses/LICENSE
investormate-0.2.0.dist-info/METADATA
investormate-0.2.0.dist-info/WHEEL
investormate-0.2.0.dist-info/top_level.txt
investormate-0.2.0.dist-info/RECORD
