Metadata-Version: 2.4
Name: investormate
Version: 0.2.0
Summary: AI-powered stock analysis package combining data, technical indicators, and multi-provider AI analysis
Author: InvestorMate Contributors
License-Expression: MIT
Project-URL: Homepage, https://github.com/siddartha19/investormate
Project-URL: Documentation, https://github.com/siddartha19/investormate#readme
Project-URL: Repository, https://github.com/siddartha19/investormate
Project-URL: Bug Tracker, https://github.com/siddartha19/investormate/issues
Keywords: finance,stocks,ai,analysis,yfinance,trading,investment,technical-analysis
Classifier: Development Status :: 3 - Alpha
Classifier: Intended Audience :: Developers
Classifier: Intended Audience :: Financial and Insurance Industry
Classifier: Programming Language :: Python :: 3
Classifier: Programming Language :: Python :: 3.9
Classifier: Programming Language :: Python :: 3.10
Classifier: Programming Language :: Python :: 3.11
Classifier: Programming Language :: Python :: 3.12
Classifier: Topic :: Office/Business :: Financial :: Investment
Classifier: Topic :: Scientific/Engineering :: Artificial Intelligence
Requires-Python: >=3.9
License-File: LICENSE
Requires-Dist: yfinance>=0.2.40
Requires-Dist: pandas>=2.0.0
Requires-Dist: numpy>=1.24.0
Requires-Dist: requests>=2.31.0
Requires-Dist: beautifulsoup4>=4.12.0
Requires-Dist: pypdf>=5.0.0
Requires-Dist: validators>=0.20.0
Provides-Extra: ai
Requires-Dist: openai>=1.0.0; extra == "ai"
Requires-Dist: anthropic>=0.30.0; extra == "ai"
Requires-Dist: google-genai>=0.1.0; extra == "ai"
Provides-Extra: ta
Requires-Dist: pandas-ta>=0.3.14b; extra == "ta"
Provides-Extra: all
Requires-Dist: openai>=1.0.0; extra == "all"
Requires-Dist: anthropic>=0.30.0; extra == "all"
Requires-Dist: google-genai>=0.1.0; extra == "all"
Requires-Dist: pandas-ta>=0.3.14b; extra == "all"
Provides-Extra: dev
Requires-Dist: pytest>=7.0.0; extra == "dev"
Requires-Dist: pytest-cov>=4.0.0; extra == "dev"
Requires-Dist: black>=23.0.0; extra == "dev"
Requires-Dist: flake8>=6.0.0; extra == "dev"
Requires-Dist: build>=1.0.0; extra == "dev"
Dynamic: license-file
